Metadata-Version: 2.1
Name: odoo14-addon-account_analytic_distribution_required
Version: 14.0.1.0.1.dev12
Summary: Account Analytic Distribution Required
Home-page: https://github.com/OCA/account-analytic
Author: ACSONE SA/NV, Tecnativa, Odoo Community Association (OCA)
Author-email: support@odoo-community.org
License: AGPL-3
Classifier: Programming Language :: Python
Classifier: Framework :: Odoo
Classifier: Framework :: Odoo :: 14.0
Classifier: License :: OSI Approved :: GNU Affero General Public License v3
Requires-Python: >=3.6
Requires-Dist: odoo14-addon-account-analytic-required
Requires-Dist: odoo<14.1dev,>=14.0a
